{
  "vipendtime": "2026-04-29 10:00:04",
  "cookie": "user_type=0; 1&_device=iPhone&37acc926-a129-4f66-8e70-208d17230ddc&2.25.1; x-intl-mulehorse-bucketIds=%2C; net-mode=WIFI; channel=ios-appstore; country_id=1; idfa=da1c89b6-b914-4773-b0ea-49a217f8d7aa; domain=apisg.himalaya.com; appsflyer_id=1777471200-1111111; locale=zh_CN; path=/; 1&_token=10007258869&8e03804c0c30b045a00b8f40535074222079; location=sg; impl=com.ximalaya.xmlyi; x-abtest-bucketIds=; JSESSIONID=",
  "email": "820157198@gmail.com",
  "uid": 10007258869,
  "token": "8e03804c0c30b045a00b8f40535074222079"
}