{
  "vipendtime": "2026-04-09 19:00:25",
  "cookie": "user_type=0; 1&_device=iPhone&6249730e-5b9b-4004-a18d-e07a6efed926&2.25.1; x-intl-mulehorse-bucketIds=%2C; net-mode=WIFI; channel=ios-appstore; country_id=1; idfa=1010d00b-f106-4102-b9ba-5bcaff85517c; domain=apisg.himalaya.com; appsflyer_id=1775721600-1111111; locale=zh_CN; path=/; 1&_token=10007231523&3a45484d01f14049390bc0c07cb0e14c1b41; location=sg; impl=com.ximalaya.xmlyi; x-abtest-bucketIds=; JSESSIONID=",
  "email": "743962981@gmail.com",
  "uid": 10007231523,
  "token": "3a45484d01f14049390bc0c07cb0e14c1b41"
}