{
  "vipendtime": "2026-05-08 04:00:08",
  "cookie": "user_type=0; 1&_device=iPhone&3e83b5e2-0ffb-4af7-afa4-850e90d8315e&2.25.1; x-intl-mulehorse-bucketIds=%2C; net-mode=WIFI; channel=ios-appstore; country_id=1; idfa=dbabf8a6-cb62-4389-b1c6-6ad6f4d34147; domain=apisg.himalaya.com; appsflyer_id=1778173200-1111111; locale=zh_CN; path=/; 1&_token=10007270112&f240e0d807f5a048da094750f6bfd12ba112; location=sg; impl=com.ximalaya.xmlyi; x-abtest-bucketIds=; JSESSIONID=",
  "email": "558114369@gmail.com",
  "uid": 10007270112,
  "token": "f240e0d807f5a048da094750f6bfd12ba112"
}