{
  "vipendtime": "2026-03-19 23:00:04",
  "cookie": "user_type=0; 1&_device=iPhone&c0b20923-4ea2-4798-8b71-f1d58741d957&2.25.1; x-intl-mulehorse-bucketIds=%2C; net-mode=WIFI; channel=ios-appstore; country_id=1; idfa=a1c87ae4-f5cb-433a-9f22-b82962b7eaa5; domain=apisg.himalaya.com; appsflyer_id=1773921601-1111111; locale=zh_CN; path=/; 1&_token=10007204599&62cd0876006ad0448c0ae4b06459b54c330a; location=sg; impl=com.ximalaya.xmlyi; x-abtest-bucketIds=; JSESSIONID=",
  "email": "508688612@gmail.com",
  "uid": 10007204599,
  "token": "62cd0876006ad0448c0ae4b06459b54c330a"
}