{
  "vipendtime": "2026-05-16 21:00:04",
  "cookie": "user_type=0; 1&_device=iPhone&235650d3-264c-43a8-a55a-9823236d48dd&2.25.1; x-intl-mulehorse-bucketIds=%2C; net-mode=WIFI; channel=ios-appstore; country_id=1; idfa=4e40f88b-976c-4cfe-8460-dce32c61b0c9; domain=apisg.himalaya.com; appsflyer_id=1778925601-1111111; locale=zh_CN; path=/; 1&_token=10007281900&0635468c02f170466709a9f0140f1ae05da8; location=sg; impl=com.ximalaya.xmlyi; x-abtest-bucketIds=; JSESSIONID=",
  "email": "720846520@gmail.com",
  "uid": 10007281900,
  "token": "0635468c02f170466709a9f0140f1ae05da8"
}