{
  "vipendtime": "2026-04-05 21:00:07",
  "cookie": "user_type=0; 1&_device=iPhone&ebb27eb0-5903-4a8d-96d4-d781a61f9707&2.25.1; x-intl-mulehorse-bucketIds=%2C; net-mode=WIFI; channel=ios-appstore; country_id=1; idfa=67d74053-fcdc-4b4c-bbe8-b78f01c097e1; domain=apisg.himalaya.com; appsflyer_id=1775383200-1111111; locale=zh_CN; path=/; 1&_token=10007227298&b3640c300a88e0471a0b75a032f5c3594bf2; location=sg; impl=com.ximalaya.xmlyi; x-abtest-bucketIds=; JSESSIONID=",
  "email": "545711258@gmail.com",
  "uid": 10007227298,
  "token": "b3640c300a88e0471a0b75a032f5c3594bf2"
}